digitalhub_core_dbt/__init__.py
digitalhub_core_dbt/entities/__init__.py
digitalhub_core_dbt/entities/functions/__init__.py
digitalhub_core_dbt/entities/functions/spec.py
digitalhub_core_dbt/entities/tasks/__init__.py
digitalhub_core_dbt/entities/tasks/spec.py
digitalhub_core_dbt/runtime/__init__.py
digitalhub_core_dbt/runtime/dbt_utils.py
digitalhub_core_dbt/runtime/parse_utils.py
digitalhub_core_dbt/runtime/runtime.py
digitalhub_core_dbt-0.0.7.dist-info/LICENSE.txt
digitalhub_core_dbt-0.0.7.dist-info/METADATA
digitalhub_core_dbt-0.0.7.dist-info/WHEEL
digitalhub_core_dbt-0.0.7.dist-info/top_level.txt
digitalhub_core_dbt-0.0.7.dist-info/RECORD
