Metadata-Version: 2.1
Name: digitalhub-core-dbt
Version: 0.0.7
Summary: DBT runtime for DHCore
Author-email: Fondazione Bruno Kessler <dslab@fbk.eu>, Matteo Martini <mmartini@fbk.eu>
License: Apache License
Project-URL: Homepage, https://github.com/scc-digitalhub/digitalhub-core/tree/main/sdk
Keywords: data,dataops,kubernetes
Classifier: License :: OSI Approved :: Apache Software License
Classifier: Programming Language :: Python :: 3.9
Classifier: Programming Language :: Python :: 3.10
Classifier: Programming Language :: Python :: 3.11
Requires-Python: >=3.9
License-File: LICENSE.txt
Requires-Dist: digitalhub-core >=0.0.5
Provides-Extra: local
Requires-Dist: dbt-postgres ==1.6.7 ; extra == 'local'
